[
    {
        "scope": "http://localhost:3000",
        "method": "GET",
        "path": "/mobify/proxy/api/product/shopper-products/v1/organizations/f_ecom_zzrf_001/products?ids=14%2C15%2C20%2C18%2C14%2C6%2C1%2C8%2C23%2C9%2C15%2C10%2C8%2C0%2C8%2C23%2C20%2C12%2C2%2C7%2C24%2C25%2C21%2C11%2C5%2C22&siteId=RefArchGlobal",
        "body": "",
        "status": 400,
        "response": {
            "title": "Bad Request",
            "type": "https://api.commercecloud.salesforce.com/documentation/error/v1/errors/validation",
            "detail": "Maximum number of products you can request in one call is 25."
        },
        "rawHeaders": [
            "date",
            "Mon, 12 Sep 2022 04:16:40 GMT",
            "content-type",
            "application/problem+json; charset=UTF-8",
            "content-length",
            "200",
            "connection",
            "close",
            "host",
            "lb001-mprd-use1.cloudhub.commercecloud.salesforce.com",
            "cf-ew-via",
            "15",
            "cdn-loop",
            "cloudflare; subreqs=1",
            "x-real-ip",
            "162.158.142.177",
            "x-forwarded-proto",
            "https",
            "cf-ray",
            "7495d43d1fef1afb-PHX",
            "accept-encoding",
            "gzip",
            "accept",
            "*/*",
            "strict-transport-security",
            "max-age=31536000; includeSubdomains;",
            "user-agent",
            "Amazon CloudFront",
            "cf-cache-status",
            "DYNAMIC",
            "_is_allowed",
            "true",
            "_sfdc_badge",
            "1fd0c2e5-f426-40d3-bf3b-e6a9ba2c22b6",
            "_sfdc_c2c_jti",
            "C2C4856201860-18906789039592946059892859",
            "_sfdc_client_id",
            "c9c45bfd-0ed3-4aa2-9971-40f88962b836",
            "_sfdc_customer_id",
            "8ade0c78-6a8a-4cd7-b63f-89e1e5b6dc57",
            "_sfdc_customer_idp",
            "slas",
            "_sfdc_customer_login",
            "guest",
            "_sfdc_customer_type",
            "guest",
            "_sfdc_customer_visit_id",
            "8ade0c78-6a8a-4cd7-b63f-89e1e5b6dc57",
            "_sfdc_jwt_iat",
            "1662956199",
            "_sfdc_org_id",
            "f_ecom_zzrf_001",
            "_sfdc_shopperjwt_type",
            "slas",
            "cf-connecting-ip",
            "13.110.54.11",
            "cf-visitor",
            "{\"scheme\":\"https\"}",
            "cf-worker",
            "commerce-api-eu.api.commercecloud.salesforce.com",
            "true-client-ip",
            "13.110.54.11",
            "x-correlation-id",
            "7495d43d1fef1afb",
            "x-forwarded-for",
            "13.110.54.11, 162.158.142.177",
            "x-forwarded-host",
            "kv7kzm78.api.commercecloud.salesforce.com",
            "x-forwarded-proto-real",
            "https",
            "x-mobify",
            "true",
            "x-ssl-client-dn",
            "/C=US/ST=California/L=San Francisco/O=salesforce.com, inc./CN=cloudflare.api.commercecloud.salesforce.com",
            "x-ssl-client-serial",
            "6283AC6B34ED9D02",
            "x-ssl-client-verify",
            "SUCCESS",
            "x-ssl-issuer",
            "/C=US/ST=California/L=San Francisco/O=salesforce.com, inc./CN=salesforce.com Internal CA PHX 2",
            "Vary",
            "Accept-Encoding",
            "server",
            "cloudflare",
            "x-proxy-request-url",
            "https://kv7kzm78.api.commercecloud.salesforce.com/product/shopper-products/v1/organizations/f_ecom_zzrf_001/products?ids=14%2C15%2C20%2C18%2C14%2C6%2C1%2C8%2C23%2C9%2C15%2C10%2C8%2C0%2C8%2C23%2C20%2C12%2C2%2C7%2C24%2C25%2C21%2C11%2C5%2C22&siteId=RefArchGlobal"
        ],
        "responseIsBinary": false
    }
]